<?xml version="1.0" encoding="UTF-8" standalone="yes"?>
<statisticalReport>
    <result>
        <sourceList xmlns:xsi="http://www.w3.org/2001/XMLSchema-instance" xsi:type="termType">
            <count>1</count>
            <expandedForm>has relationship other than synonymous, narrower, or broader/Has inherent location</expandedForm>
            <termType>RO/has_inherent_location</termType>
            <totalCountValidation>0</totalCountValidation>
        </sourceList>
        <sourceList xmlns:xsi="http://www.w3.org/2001/XMLSchema-instance" xsi:type="termType">
            <count>1</count>
            <expandedForm>has relationship other than synonymous, narrower, or broader/Inherent location of</expandedForm>
            <termType>RO/inherent_location_of</termType>
            <totalCountValidation>0</totalCountValidation>
        </sourceList>
        <sourceList xmlns:xsi="http://www.w3.org/2001/XMLSchema-instance" xsi:type="termType">
            <count>2</count>
            <expandedForm>has relationship other than synonymous, narrower, or broader/Part referred to by</expandedForm>
            <termType>RO/part_referred_to_by</termType>
            <totalCountValidation>0</totalCountValidation>
        </sourceList>
        <sourceList xmlns:xsi="http://www.w3.org/2001/XMLSchema-instance" xsi:type="termType">
            <count>2</count>
            <expandedForm>has relationship other than synonymous, narrower, or broader/Relative to part of</expandedForm>
            <termType>RO/relative_to_part_of</termType>
            <totalCountValidation>0</totalCountValidation>
        </sourceList>
        <sourceList xmlns:xsi="http://www.w3.org/2001/XMLSchema-instance" xsi:type="termType">
            <count>6</count>
            <expandedForm>has relationship other than synonymous, narrower, or broader/Dependent of</expandedForm>
            <termType>RO/dependent_of</termType>
            <totalCountValidation>0</totalCountValidation>
        </sourceList>
        <sourceList xmlns:xsi="http://www.w3.org/2001/XMLSchema-instance" xsi:type="termType">
            <count>6</count>
            <expandedForm>has relationship other than synonymous, narrower, or broader/Has dependent</expandedForm>
            <termType>RO/has_dependent</termType>
            <totalCountValidation>0</totalCountValidation>
        </sourceList>
        <sourceList xmlns:xsi="http://www.w3.org/2001/XMLSchema-instance" xsi:type="termType">
            <count>8</count>
            <expandedForm>has relationship other than synonymous, narrower, or broader/Has stage</expandedForm>
            <termType>RO/has_stage</termType>
            <totalCountValidation>0</totalCountValidation>
        </sourceList>
        <sourceList xmlns:xsi="http://www.w3.org/2001/XMLSchema-instance" xsi:type="termType">
            <count>8</count>
            <expandedForm>has relationship other than synonymous, narrower, or broader/Stage of</expandedForm>
            <termType>RO/stage_of</termType>
            <totalCountValidation>0</totalCountValidation>
        </sourceList>
        <sourceList xmlns:xsi="http://www.w3.org/2001/XMLSchema-instance" xsi:type="termType">
            <count>11</count>
            <expandedForm>has relationship other than synonymous, narrower, or broader/Process output of</expandedForm>
            <termType>RO/process_output_of</termType>
            <totalCountValidation>0</totalCountValidation>
        </sourceList>
        <sourceList xmlns:xsi="http://www.w3.org/2001/XMLSchema-instance" xsi:type="termType">
            <count>11</count>
            <expandedForm>has relationship other than synonymous, narrower, or broader/Has process output</expandedForm>
            <termType>RO/has_process_output</termType>
            <totalCountValidation>0</totalCountValidation>
        </sourceList>
        <sourceList xmlns:xsi="http://www.w3.org/2001/XMLSchema-instance" xsi:type="termType">
            <count>12</count>
            <expandedForm>has relationship other than synonymous, narrower, or broader/Has precondition</expandedForm>
            <termType>RO/has_precondition</termType>
            <totalCountValidation>0</totalCountValidation>
        </sourceList>
        <sourceList xmlns:xsi="http://www.w3.org/2001/XMLSchema-instance" xsi:type="termType">
            <count>12</count>
            <expandedForm>has relationship other than synonymous, narrower, or broader/Precondition of</expandedForm>
            <termType>RO/precondition_of</termType>
            <totalCountValidation>0</totalCountValidation>
        </sourceList>
        <sourceList xmlns:xsi="http://www.w3.org/2001/XMLSchema-instance" xsi:type="termType">
            <count>14</count>
            <expandedForm>has relationship other than synonymous, narrower, or broader/Has technique</expandedForm>
            <termType>RO/has_technique</termType>
            <totalCountValidation>0</totalCountValidation>
        </sourceList>
        <sourceList xmlns:xsi="http://www.w3.org/2001/XMLSchema-instance" xsi:type="termType">
            <count>14</count>
            <expandedForm>has relationship other than synonymous, narrower, or broader/Technique of</expandedForm>
            <termType>RO/technique_of</termType>
            <totalCountValidation>0</totalCountValidation>
        </sourceList>
        <sourceList xmlns:xsi="http://www.w3.org/2001/XMLSchema-instance" xsi:type="termType">
            <count>23</count>
            <expandedForm>has relationship other than synonymous, narrower, or broader/Has time aspect</expandedForm>
            <termType>RO/has_time_aspect</termType>
            <totalCountValidation>0</totalCountValidation>
        </sourceList>
        <sourceList xmlns:xsi="http://www.w3.org/2001/XMLSchema-instance" xsi:type="termType">
            <count>23</count>
            <expandedForm>has relationship other than synonymous, narrower, or broader/Time aspect of</expandedForm>
            <termType>RO/time_aspect_of</termType>
            <totalCountValidation>0</totalCountValidation>
        </sourceList>
        <sourceList xmlns:xsi="http://www.w3.org/2001/XMLSchema-instance" xsi:type="termType">
            <count>26</count>
            <expandedForm>has relationship other than synonymous, narrower, or broader/Has location</expandedForm>
            <termType>RO/has_location</termType>
            <totalCountValidation>0</totalCountValidation>
        </sourceList>
        <sourceList xmlns:xsi="http://www.w3.org/2001/XMLSchema-instance" xsi:type="termType">
            <count>26</count>
            <expandedForm>has relationship other than synonymous, narrower, or broader/Location of</expandedForm>
            <termType>RO/location_of</termType>
            <totalCountValidation>0</totalCountValidation>
        </sourceList>
        <sourceList xmlns:xsi="http://www.w3.org/2001/XMLSchema-instance" xsi:type="termType">
            <count>27</count>
            <expandedForm>has relationship other than synonymous, narrower, or broader/Has direct site</expandedForm>
            <termType>RO/has_direct_site</termType>
            <totalCountValidation>0</totalCountValidation>
        </sourceList>
        <sourceList xmlns:xsi="http://www.w3.org/2001/XMLSchema-instance" xsi:type="termType">
            <count>27</count>
            <expandedForm>has relationship other than synonymous, narrower, or broader/Direct site of</expandedForm>
            <termType>RO/direct_site_of</termType>
            <totalCountValidation>0</totalCountValidation>
        </sourceList>
        <sourceList xmlns:xsi="http://www.w3.org/2001/XMLSchema-instance" xsi:type="termType">
            <count>55</count>
            <expandedForm>has relationship other than synonymous, narrower, or broader/Has measurement method</expandedForm>
            <termType>RO/has_measurement_method</termType>
            <totalCountValidation>0</totalCountValidation>
        </sourceList>
        <sourceList xmlns:xsi="http://www.w3.org/2001/XMLSchema-instance" xsi:type="termType">
            <count>55</count>
            <expandedForm>has relationship other than synonymous, narrower, or broader/Measurement method of</expandedForm>
            <termType>RO/measurement_method_of</termType>
            <totalCountValidation>0</totalCountValidation>
        </sourceList>
        <sourceList xmlns:xsi="http://www.w3.org/2001/XMLSchema-instance" xsi:type="termType">
            <count>60</count>
            <expandedForm>has relationship other than synonymous, narrower, or broader/Temporally related to</expandedForm>
            <termType>RO/temporally_related_to</termType>
            <totalCountValidation>0</totalCountValidation>
        </sourceList>
        <sourceList xmlns:xsi="http://www.w3.org/2001/XMLSchema-instance" xsi:type="termType">
            <count>64</count>
            <expandedForm>has relationship other than synonymous, narrower, or broader/Has associated function</expandedForm>
            <termType>RO/has_associated_function</termType>
            <totalCountValidation>0</totalCountValidation>
        </sourceList>
        <sourceList xmlns:xsi="http://www.w3.org/2001/XMLSchema-instance" xsi:type="termType">
            <count>64</count>
            <expandedForm>has relationship other than synonymous, narrower, or broader/Associated function of</expandedForm>
            <termType>RO/associated_function_of</termType>
            <totalCountValidation>0</totalCountValidation>
        </sourceList>
        <sourceList xmlns:xsi="http://www.w3.org/2001/XMLSchema-instance" xsi:type="termType">
            <count>78</count>
            <expandedForm>has relationship other than synonymous, narrower, or broader/Measures</expandedForm>
            <termType>RO/measures</termType>
            <totalCountValidation>0</totalCountValidation>
        </sourceList>
        <sourceList xmlns:xsi="http://www.w3.org/2001/XMLSchema-instance" xsi:type="termType">
            <count>78</count>
            <expandedForm>has relationship other than synonymous, narrower, or broader/Measured by</expandedForm>
            <termType>RO/measured_by</termType>
            <totalCountValidation>0</totalCountValidation>
        </sourceList>
        <sourceList xmlns:xsi="http://www.w3.org/2001/XMLSchema-instance" xsi:type="termType">
            <count>123</count>
            <expandedForm>has relationship other than synonymous, narrower, or broader/During</expandedForm>
            <termType>RO/during</termType>
            <totalCountValidation>0</totalCountValidation>
        </sourceList>
        <sourceList xmlns:xsi="http://www.w3.org/2001/XMLSchema-instance" xsi:type="termType">
            <count>123</count>
            <expandedForm>has relationship other than synonymous, narrower, or broader/Inverse during</expandedForm>
            <termType>RO/inverse_during</termType>
            <totalCountValidation>0</totalCountValidation>
        </sourceList>
        <sourceList xmlns:xsi="http://www.w3.org/2001/XMLSchema-instance" xsi:type="termType">
            <count>127</count>
            <expandedForm>has relationship other than synonymous, narrower, or broader/Characterizes</expandedForm>
            <termType>RO/characterizes</termType>
            <totalCountValidation>0</totalCountValidation>
        </sourceList>
        <sourceList xmlns:xsi="http://www.w3.org/2001/XMLSchema-instance" xsi:type="termType">
            <count>127</count>
            <expandedForm>has relationship other than synonymous, narrower, or broader/Characterized by</expandedForm>
            <termType>RO/characterized_by</termType>
            <totalCountValidation>0</totalCountValidation>
        </sourceList>
        <sourceList xmlns:xsi="http://www.w3.org/2001/XMLSchema-instance" xsi:type="termType">
            <count>132</count>
            <expandedForm>has relationship other than synonymous, narrower, or broader/State of matter of</expandedForm>
            <termType>RO/state_of_matter_of</termType>
            <totalCountValidation>0</totalCountValidation>
        </sourceList>
        <sourceList xmlns:xsi="http://www.w3.org/2001/XMLSchema-instance" xsi:type="termType">
            <count>132</count>
            <expandedForm>has relationship other than synonymous, narrower, or broader/Has state of matter</expandedForm>
            <termType>RO/has_state_of_matter</termType>
            <totalCountValidation>0</totalCountValidation>
        </sourceList>
        <sourceList xmlns:xsi="http://www.w3.org/2001/XMLSchema-instance" xsi:type="termType">
            <count>156</count>
            <expandedForm>has relationship other than synonymous, narrower, or broader/Inheres in</expandedForm>
            <termType>RO/inheres_in</termType>
            <totalCountValidation>0</totalCountValidation>
        </sourceList>
        <sourceList xmlns:xsi="http://www.w3.org/2001/XMLSchema-instance" xsi:type="termType">
            <count>156</count>
            <expandedForm>has relationship other than synonymous, narrower, or broader/Has recipient category</expandedForm>
            <termType>RO/has_recipient_category</termType>
            <totalCountValidation>0</totalCountValidation>
        </sourceList>
        <sourceList xmlns:xsi="http://www.w3.org/2001/XMLSchema-instance" xsi:type="termType">
            <count>156</count>
            <expandedForm>has relationship other than synonymous, narrower, or broader/Recipient category of</expandedForm>
            <termType>RO/recipient_category_of</termType>
            <totalCountValidation>0</totalCountValidation>
        </sourceList>
        <sourceList xmlns:xsi="http://www.w3.org/2001/XMLSchema-instance" xsi:type="termType">
            <count>156</count>
            <expandedForm>has relationship other than synonymous, narrower, or broader/Has inherent attribute</expandedForm>
            <termType>RO/has_inherent_attribute</termType>
            <totalCountValidation>0</totalCountValidation>
        </sourceList>
        <sourceList xmlns:xsi="http://www.w3.org/2001/XMLSchema-instance" xsi:type="termType">
            <count>167</count>
            <expandedForm>has relationship other than synonymous, narrower, or broader/Property type of</expandedForm>
            <termType>RO/property_type_of</termType>
            <totalCountValidation>0</totalCountValidation>
        </sourceList>
        <sourceList xmlns:xsi="http://www.w3.org/2001/XMLSchema-instance" xsi:type="termType">
            <count>167</count>
            <expandedForm>has relationship other than synonymous, narrower, or broader/Has property type</expandedForm>
            <termType>RO/has_property_type</termType>
            <totalCountValidation>0</totalCountValidation>
        </sourceList>
        <sourceList xmlns:xsi="http://www.w3.org/2001/XMLSchema-instance" xsi:type="termType">
            <count>181</count>
            <expandedForm>has a broader relationship/Alternative of</expandedForm>
            <termType>RB/alternative_of</termType>
            <totalCountValidation>0</totalCountValidation>
        </sourceList>
        <sourceList xmlns:xsi="http://www.w3.org/2001/XMLSchema-instance" xsi:type="termType">
            <count>181</count>
            <expandedForm>has a narrower relationship/Has alternative</expandedForm>
            <termType>RN/has_alternative</termType>
            <totalCountValidation>0</totalCountValidation>
        </sourceList>
        <sourceList xmlns:xsi="http://www.w3.org/2001/XMLSchema-instance" xsi:type="termType">
            <count>191</count>
            <expandedForm>has relationship other than synonymous, narrower, or broader/Has episodicity</expandedForm>
            <termType>RO/has_episodicity</termType>
            <totalCountValidation>0</totalCountValidation>
        </sourceList>
        <sourceList xmlns:xsi="http://www.w3.org/2001/XMLSchema-instance" xsi:type="termType">
            <count>191</count>
            <expandedForm>has relationship other than synonymous, narrower, or broader/Episodicity of</expandedForm>
            <termType>RO/episodicity_of</termType>
            <totalCountValidation>0</totalCountValidation>
        </sourceList>
        <sourceList xmlns:xsi="http://www.w3.org/2001/XMLSchema-instance" xsi:type="termType">
            <count>200</count>
            <expandedForm>has relationship other than synonymous, narrower, or broader/Has indirect device</expandedForm>
            <termType>RO/has_indirect_device</termType>
            <totalCountValidation>0</totalCountValidation>
        </sourceList>
        <sourceList xmlns:xsi="http://www.w3.org/2001/XMLSchema-instance" xsi:type="termType">
            <count>200</count>
            <expandedForm>has relationship other than synonymous, narrower, or broader/Indirect device of</expandedForm>
            <termType>RO/indirect_device_of</termType>
            <totalCountValidation>0</totalCountValidation>
        </sourceList>
        <sourceList xmlns:xsi="http://www.w3.org/2001/XMLSchema-instance" xsi:type="termType">
            <count>271</count>
            <expandedForm>has relationship other than synonymous, narrower, or broader/Specimen source morphology of</expandedForm>
            <termType>RO/specimen_source_morphology_of</termType>
            <totalCountValidation>0</totalCountValidation>
        </sourceList>
        <sourceList xmlns:xsi="http://www.w3.org/2001/XMLSchema-instance" xsi:type="termType">
            <count>271</count>
            <expandedForm>has relationship other than synonymous, narrower, or broader/Has specimen source morphology</expandedForm>
            <termType>RO/has_specimen_source_morphology</termType>
            <totalCountValidation>0</totalCountValidation>
        </sourceList>
        <sourceList xmlns:xsi="http://www.w3.org/2001/XMLSchema-instance" xsi:type="termType">
            <count>283</count>
            <expandedForm>has relationship other than synonymous, narrower, or broader/Has subject of information</expandedForm>
            <termType>RO/has_subject_of_information</termType>
            <totalCountValidation>0</totalCountValidation>
        </sourceList>
        <sourceList xmlns:xsi="http://www.w3.org/2001/XMLSchema-instance" xsi:type="termType">
            <count>283</count>
            <expandedForm>has relationship other than synonymous, narrower, or broader/Subject of information of</expandedForm>
            <termType>RO/subject_of_information_of</termType>
            <totalCountValidation>0</totalCountValidation>
        </sourceList>
        <sourceList xmlns:xsi="http://www.w3.org/2001/XMLSchema-instance" xsi:type="termType">
            <count>295</count>
            <expandedForm>has relationship other than synonymous, narrower, or broader/Dose form transformation of</expandedForm>
            <termType>RO/dose_form_transformation_of</termType>
            <totalCountValidation>0</totalCountValidation>
        </sourceList>
        <sourceList xmlns:xsi="http://www.w3.org/2001/XMLSchema-instance" xsi:type="termType">
            <count>295</count>
            <expandedForm>has relationship other than synonymous, narrower, or broader/Has dose form transformation</expandedForm>
            <termType>RO/has_dose_form_transformation</termType>
            <totalCountValidation>0</totalCountValidation>
        </sourceList>
        <sourceList xmlns:xsi="http://www.w3.org/2001/XMLSchema-instance" xsi:type="termType">
            <count>297</count>
            <expandedForm>has relationship other than synonymous, narrower, or broader/Has basic dose form</expandedForm>
            <termType>RO/has_basic_dose_form</termType>
            <totalCountValidation>0</totalCountValidation>
        </sourceList>
        <sourceList xmlns:xsi="http://www.w3.org/2001/XMLSchema-instance" xsi:type="termType">
            <count>297</count>
            <expandedForm>has relationship other than synonymous, narrower, or broader/Basic dose form of</expandedForm>
            <termType>RO/basic_dose_form_of</termType>
            <totalCountValidation>0</totalCountValidation>
        </sourceList>
        <sourceList xmlns:xsi="http://www.w3.org/2001/XMLSchema-instance" xsi:type="termType">
            <count>311</count>
            <expandedForm>has relationship other than synonymous, narrower, or broader/Has dose form release characteristic</expandedForm>
            <termType>RO/has_dose_form_release_characteristic</termType>
            <totalCountValidation>0</totalCountValidation>
        </sourceList>
        <sourceList xmlns:xsi="http://www.w3.org/2001/XMLSchema-instance" xsi:type="termType">
            <count>311</count>
            <expandedForm>has relationship other than synonymous, narrower, or broader/Dose form release characteristic of</expandedForm>
            <termType>RO/dose_form_release_characteristic_of</termType>
            <totalCountValidation>0</totalCountValidation>
        </sourceList>
        <sourceList xmlns:xsi="http://www.w3.org/2001/XMLSchema-instance" xsi:type="termType">
            <count>311</count>
            <expandedForm>has relationship other than synonymous, narrower, or broader/Dose form administration method of</expandedForm>
            <termType>RO/dose_form_administration_method_of</termType>
            <totalCountValidation>0</totalCountValidation>
        </sourceList>
        <sourceList xmlns:xsi="http://www.w3.org/2001/XMLSchema-instance" xsi:type="termType">
            <count>311</count>
            <expandedForm>has relationship other than synonymous, narrower, or broader/Has dose form administration method</expandedForm>
            <termType>RO/has_dose_form_administration_method</termType>
            <totalCountValidation>0</totalCountValidation>
        </sourceList>
        <sourceList xmlns:xsi="http://www.w3.org/2001/XMLSchema-instance" xsi:type="termType">
            <count>326</count>
            <expandedForm>has relationship other than synonymous, narrower, or broader/Part anatomy structure of</expandedForm>
            <termType>RO/part_anatomy_structure_of</termType>
            <totalCountValidation>0</totalCountValidation>
        </sourceList>
        <sourceList xmlns:xsi="http://www.w3.org/2001/XMLSchema-instance" xsi:type="termType">
            <count>326</count>
            <expandedForm>has relationship other than synonymous, narrower, or broader/Has part anatomy structure</expandedForm>
            <termType>RO/has_part_anatomy_structure</termType>
            <totalCountValidation>0</totalCountValidation>
        </sourceList>
        <sourceList xmlns:xsi="http://www.w3.org/2001/XMLSchema-instance" xsi:type="termType">
            <count>338</count>
            <expandedForm>has relationship other than synonymous, narrower, or broader/Route of administration of</expandedForm>
            <termType>RO/route_of_administration_of</termType>
            <totalCountValidation>0</totalCountValidation>
        </sourceList>
        <sourceList xmlns:xsi="http://www.w3.org/2001/XMLSchema-instance" xsi:type="termType">
            <count>338</count>
            <expandedForm>has relationship other than synonymous, narrower, or broader/Has route of administration</expandedForm>
            <termType>RO/has_route_of_administration</termType>
            <totalCountValidation>0</totalCountValidation>
        </sourceList>
        <sourceList xmlns:xsi="http://www.w3.org/2001/XMLSchema-instance" xsi:type="termType">
            <count>360</count>
            <expandedForm>has relationship other than synonymous, narrower, or broader/Has dose form intended site</expandedForm>
            <termType>RO/has_dose_form_intended_site</termType>
            <totalCountValidation>0</totalCountValidation>
        </sourceList>
        <sourceList xmlns:xsi="http://www.w3.org/2001/XMLSchema-instance" xsi:type="termType">
            <count>360</count>
            <expandedForm>has relationship other than synonymous, narrower, or broader/Dose form intended site of</expandedForm>
            <termType>RO/dose_form_intended_site_of</termType>
            <totalCountValidation>0</totalCountValidation>
        </sourceList>
        <sourceList xmlns:xsi="http://www.w3.org/2001/XMLSchema-instance" xsi:type="termType">
            <count>368</count>
            <expandedForm>has relationship other than synonymous, narrower, or broader/Instrumentation of</expandedForm>
            <termType>RO/instrumentation_of</termType>
            <totalCountValidation>0</totalCountValidation>
        </sourceList>
        <sourceList xmlns:xsi="http://www.w3.org/2001/XMLSchema-instance" xsi:type="termType">
            <count>368</count>
            <expandedForm>has relationship other than synonymous, narrower, or broader/Has instrumentation</expandedForm>
            <termType>RO/has_instrumentation</termType>
            <totalCountValidation>0</totalCountValidation>
        </sourceList>
        <sourceList xmlns:xsi="http://www.w3.org/2001/XMLSchema-instance" xsi:type="termType">
            <count>399</count>
            <expandedForm>has relationship other than synonymous, narrower, or broader/Scale type of</expandedForm>
            <termType>RO/scale_type_of</termType>
            <totalCountValidation>0</totalCountValidation>
        </sourceList>
        <sourceList xmlns:xsi="http://www.w3.org/2001/XMLSchema-instance" xsi:type="termType">
            <count>399</count>
            <expandedForm>has relationship other than synonymous, narrower, or broader/Has scale type</expandedForm>
            <termType>RO/has_scale_type</termType>
            <totalCountValidation>0</totalCountValidation>
        </sourceList>
        <sourceList xmlns:xsi="http://www.w3.org/2001/XMLSchema-instance" xsi:type="termType">
            <count>399</count>
            <expandedForm>has relationship other than synonymous, narrower, or broader/Has specimen source identity</expandedForm>
            <termType>RO/has_specimen_source_identity</termType>
            <totalCountValidation>0</totalCountValidation>
        </sourceList>
        <sourceList xmlns:xsi="http://www.w3.org/2001/XMLSchema-instance" xsi:type="termType">
            <count>399</count>
            <expandedForm>has relationship other than synonymous, narrower, or broader/Specimen source identity of</expandedForm>
            <termType>RO/specimen_source_identity_of</termType>
            <totalCountValidation>0</totalCountValidation>
        </sourceList>
        <sourceList xmlns:xsi="http://www.w3.org/2001/XMLSchema-instance" xsi:type="termType">
            <count>404</count>
            <expandedForm>has relationship other than synonymous, narrower, or broader/Has property</expandedForm>
            <termType>RO/has_property</termType>
            <totalCountValidation>0</totalCountValidation>
        </sourceList>
        <sourceList xmlns:xsi="http://www.w3.org/2001/XMLSchema-instance" xsi:type="termType">
            <count>404</count>
            <expandedForm>has relationship other than synonymous, narrower, or broader/Property of</expandedForm>
            <termType>RO/property_of</termType>
            <totalCountValidation>0</totalCountValidation>
        </sourceList>
        <sourceList xmlns:xsi="http://www.w3.org/2001/XMLSchema-instance" xsi:type="termType">
            <count>535</count>
            <expandedForm>has relationship other than synonymous, narrower, or broader/Has severity</expandedForm>
            <termType>RO/has_severity</termType>
            <totalCountValidation>0</totalCountValidation>
        </sourceList>
        <sourceList xmlns:xsi="http://www.w3.org/2001/XMLSchema-instance" xsi:type="termType">
            <count>535</count>
            <expandedForm>has relationship other than synonymous, narrower, or broader/Severity of</expandedForm>
            <termType>RO/severity_of</termType>
            <totalCountValidation>0</totalCountValidation>
        </sourceList>
        <sourceList xmlns:xsi="http://www.w3.org/2001/XMLSchema-instance" xsi:type="termType">
            <count>654</count>
            <expandedForm>has relationship other than synonymous, narrower, or broader/Energy used by</expandedForm>
            <termType>RO/energy_used_by</termType>
            <totalCountValidation>0</totalCountValidation>
        </sourceList>
        <sourceList xmlns:xsi="http://www.w3.org/2001/XMLSchema-instance" xsi:type="termType">
            <count>654</count>
            <expandedForm>has relationship other than synonymous, narrower, or broader/Uses energy</expandedForm>
            <termType>RO/uses_energy</termType>
            <totalCountValidation>0</totalCountValidation>
        </sourceList>
        <sourceList xmlns:xsi="http://www.w3.org/2001/XMLSchema-instance" xsi:type="termType">
            <count>702</count>
            <expandedForm>has relationship other than synonymous, narrower, or broader/Associated etiologic finding of</expandedForm>
            <termType>RO/associated_etiologic_finding_of</termType>
            <totalCountValidation>0</totalCountValidation>
        </sourceList>
        <sourceList xmlns:xsi="http://www.w3.org/2001/XMLSchema-instance" xsi:type="termType">
            <count>702</count>
            <expandedForm>has relationship other than synonymous, narrower, or broader/Has associated etiologic finding</expandedForm>
            <termType>RO/has_associated_etiologic_finding</termType>
            <totalCountValidation>0</totalCountValidation>
        </sourceList>
        <sourceList xmlns:xsi="http://www.w3.org/2001/XMLSchema-instance" xsi:type="termType">
            <count>847</count>
            <expandedForm>has relationship other than synonymous, narrower, or broader/Procedure morphology of</expandedForm>
            <termType>RO/procedure_morphology_of</termType>
            <totalCountValidation>0</totalCountValidation>
        </sourceList>
        <sourceList xmlns:xsi="http://www.w3.org/2001/XMLSchema-instance" xsi:type="termType">
            <count>847</count>
            <expandedForm>has relationship other than synonymous, narrower, or broader/Has procedure morphology</expandedForm>
            <termType>RO/has_procedure_morphology</termType>
            <totalCountValidation>0</totalCountValidation>
        </sourceList>
        <sourceList xmlns:xsi="http://www.w3.org/2001/XMLSchema-instance" xsi:type="termType">
            <count>988</count>
            <expandedForm>has relationship other than synonymous, narrower, or broader/Has onset</expandedForm>
            <termType>RO/has_onset</termType>
            <totalCountValidation>0</totalCountValidation>
        </sourceList>
        <sourceList xmlns:xsi="http://www.w3.org/2001/XMLSchema-instance" xsi:type="termType">
            <count>988</count>
            <expandedForm>has relationship other than synonymous, narrower, or broader/Onset of</expandedForm>
            <termType>RO/onset_of</termType>
            <totalCountValidation>0</totalCountValidation>
        </sourceList>
        <sourceList xmlns:xsi="http://www.w3.org/2001/XMLSchema-instance" xsi:type="termType">
            <count>1017</count>
            <expandedForm>has relationship other than synonymous, narrower, or broader/Has procedure device</expandedForm>
            <termType>RO/has_procedure_device</termType>
            <totalCountValidation>0</totalCountValidation>
        </sourceList>
        <sourceList xmlns:xsi="http://www.w3.org/2001/XMLSchema-instance" xsi:type="termType">
            <count>1017</count>
            <expandedForm>has relationship other than synonymous, narrower, or broader/Procedure device of</expandedForm>
            <termType>RO/procedure_device_of</termType>
            <totalCountValidation>0</totalCountValidation>
        </sourceList>
        <sourceList xmlns:xsi="http://www.w3.org/2001/XMLSchema-instance" xsi:type="termType">
            <count>1096</count>
            <expandedForm>has relationship other than synonymous, narrower, or broader/Role played by</expandedForm>
            <termType>RO/role_played_by</termType>
            <totalCountValidation>0</totalCountValidation>
        </sourceList>
        <sourceList xmlns:xsi="http://www.w3.org/2001/XMLSchema-instance" xsi:type="termType">
            <count>1096</count>
            <expandedForm>has relationship other than synonymous, narrower, or broader/Plays role</expandedForm>
            <termType>RO/plays_role</termType>
            <totalCountValidation>0</totalCountValidation>
        </sourceList>
        <sourceList xmlns:xsi="http://www.w3.org/2001/XMLSchema-instance" xsi:type="termType">
            <count>1272</count>
            <expandedForm>has a narrower relationship/refers to</expandedForm>
            <termType>RN/refers_to</termType>
            <totalCountValidation>0</totalCountValidation>
        </sourceList>
        <sourceList xmlns:xsi="http://www.w3.org/2001/XMLSchema-instance" xsi:type="termType">
            <count>1272</count>
            <expandedForm>has a broader relationship/referred to by</expandedForm>
            <termType>RB/referred_to_by</termType>
            <totalCountValidation>0</totalCountValidation>
        </sourceList>
        <sourceList xmlns:xsi="http://www.w3.org/2001/XMLSchema-instance" xsi:type="termType">
            <count>1305</count>
            <expandedForm>has relationship other than synonymous, narrower, or broader/Has extent</expandedForm>
            <termType>RO/has_extent</termType>
            <totalCountValidation>0</totalCountValidation>
        </sourceList>
        <sourceList xmlns:xsi="http://www.w3.org/2001/XMLSchema-instance" xsi:type="termType">
            <count>1305</count>
            <expandedForm>has relationship other than synonymous, narrower, or broader/Extent of</expandedForm>
            <termType>RO/extent_of</termType>
            <totalCountValidation>0</totalCountValidation>
        </sourceList>
        <sourceList xmlns:xsi="http://www.w3.org/2001/XMLSchema-instance" xsi:type="termType">
            <count>1471</count>
            <expandedForm>has relationship other than synonymous, narrower, or broader/Has realization</expandedForm>
            <termType>RO/has_realization</termType>
            <totalCountValidation>0</totalCountValidation>
        </sourceList>
        <sourceList xmlns:xsi="http://www.w3.org/2001/XMLSchema-instance" xsi:type="termType">
            <count>1471</count>
            <expandedForm>has relationship other than synonymous, narrower, or broader/Realization of</expandedForm>
            <termType>RO/realization_of</termType>
            <totalCountValidation>0</totalCountValidation>
        </sourceList>
        <sourceList xmlns:xsi="http://www.w3.org/2001/XMLSchema-instance" xsi:type="termType">
            <count>1520</count>
            <expandedForm>has relationship other than synonymous, narrower, or broader/has surgical approach</expandedForm>
            <termType>RO/has_surgical_approach</termType>
            <totalCountValidation>0</totalCountValidation>
        </sourceList>
        <sourceList xmlns:xsi="http://www.w3.org/2001/XMLSchema-instance" xsi:type="termType">
            <count>1520</count>
            <expandedForm>has relationship other than synonymous, narrower, or broader/surgical approach of</expandedForm>
            <termType>RO/surgical_approach_of</termType>
            <totalCountValidation>0</totalCountValidation>
        </sourceList>
        <sourceList xmlns:xsi="http://www.w3.org/2001/XMLSchema-instance" xsi:type="termType">
            <count>1590</count>
            <expandedForm>has relationship other than synonymous, narrower, or broader/Has communication with wound</expandedForm>
            <termType>RO/has_communication_with_wound</termType>
            <totalCountValidation>0</totalCountValidation>
        </sourceList>
        <sourceList xmlns:xsi="http://www.w3.org/2001/XMLSchema-instance" xsi:type="termType">
            <count>1590</count>
            <expandedForm>has relationship other than synonymous, narrower, or broader/Wound has communication with</expandedForm>
            <termType>RO/wound_has_communication_with</termType>
            <totalCountValidation>0</totalCountValidation>
        </sourceList>
        <sourceList xmlns:xsi="http://www.w3.org/2001/XMLSchema-instance" xsi:type="termType">
            <count>1764</count>
            <expandedForm>has relationship other than synonymous, narrower, or broader/Has indirect morphology</expandedForm>
            <termType>RO/has_indirect_morphology</termType>
            <totalCountValidation>0</totalCountValidation>
        </sourceList>
        <sourceList xmlns:xsi="http://www.w3.org/2001/XMLSchema-instance" xsi:type="termType">
            <count>1764</count>
            <expandedForm>has relationship other than synonymous, narrower, or broader/Indirect morphology of</expandedForm>
            <termType>RO/indirect_morphology_of</termType>
            <totalCountValidation>0</totalCountValidation>
        </sourceList>
        <sourceList xmlns:xsi="http://www.w3.org/2001/XMLSchema-instance" xsi:type="termType">
            <count>1882</count>
            <expandedForm>has relationship other than synonymous, narrower, or broader/Specimen substance of</expandedForm>
            <termType>RO/specimen_substance_of</termType>
            <totalCountValidation>0</totalCountValidation>
        </sourceList>
        <sourceList xmlns:xsi="http://www.w3.org/2001/XMLSchema-instance" xsi:type="termType">
            <count>1882</count>
            <expandedForm>has relationship other than synonymous, narrower, or broader/Has specimen substance</expandedForm>
            <termType>RO/has_specimen_substance</termType>
            <totalCountValidation>0</totalCountValidation>
        </sourceList>
        <sourceList xmlns:xsi="http://www.w3.org/2001/XMLSchema-instance" xsi:type="termType">
            <count>1966</count>
            <expandedForm>has relationship other than synonymous, narrower, or broader/Has specimen procedure</expandedForm>
            <termType>RO/has_specimen_procedure</termType>
            <totalCountValidation>0</totalCountValidation>
        </sourceList>
        <sourceList xmlns:xsi="http://www.w3.org/2001/XMLSchema-instance" xsi:type="termType">
            <count>1966</count>
            <expandedForm>has relationship other than synonymous, narrower, or broader/Specimen procedure of</expandedForm>
            <termType>RO/specimen_procedure_of</termType>
            <totalCountValidation>0</totalCountValidation>
        </sourceList>
        <sourceList xmlns:xsi="http://www.w3.org/2001/XMLSchema-instance" xsi:type="termType">
            <count>1985</count>
            <expandedForm>has relationship other than synonymous, narrower, or broader/Has priority</expandedForm>
            <termType>RO/has_priority</termType>
            <totalCountValidation>0</totalCountValidation>
        </sourceList>
        <sourceList xmlns:xsi="http://www.w3.org/2001/XMLSchema-instance" xsi:type="termType">
            <count>1985</count>
            <expandedForm>has relationship other than synonymous, narrower, or broader/Priority of</expandedForm>
            <termType>RO/priority_of</termType>
            <totalCountValidation>0</totalCountValidation>
        </sourceList>
        <sourceList xmlns:xsi="http://www.w3.org/2001/XMLSchema-instance" xsi:type="termType">
            <count>2176</count>
            <expandedForm>has relationship other than synonymous, narrower, or broader/Is modification of</expandedForm>
            <termType>RO/is_modification_of</termType>
            <totalCountValidation>0</totalCountValidation>
        </sourceList>
        <sourceList xmlns:xsi="http://www.w3.org/2001/XMLSchema-instance" xsi:type="termType">
            <count>2176</count>
            <expandedForm>has relationship other than synonymous, narrower, or broader/Has modification</expandedForm>
            <termType>RO/has_modification</termType>
            <totalCountValidation>0</totalCountValidation>
        </sourceList>
        <sourceList xmlns:xsi="http://www.w3.org/2001/XMLSchema-instance" xsi:type="termType">
            <count>2597</count>
            <expandedForm>has relationship other than synonymous, narrower, or broader/Finding informer of</expandedForm>
            <termType>RO/finding_informer_of</termType>
            <totalCountValidation>0</totalCountValidation>
        </sourceList>
        <sourceList xmlns:xsi="http://www.w3.org/2001/XMLSchema-instance" xsi:type="termType">
            <count>2597</count>
            <expandedForm>has relationship other than synonymous, narrower, or broader/Has finding informer</expandedForm>
            <termType>RO/has_finding_informer</termType>
            <totalCountValidation>0</totalCountValidation>
        </sourceList>
        <sourceList xmlns:xsi="http://www.w3.org/2001/XMLSchema-instance" xsi:type="termType">
            <count>2947</count>
            <expandedForm>has relationship other than synonymous, narrower, or broader/Has concentration strength denominator value</expandedForm>
            <termType>RO/has_concentration_strength_denominator_value</termType>
            <totalCountValidation>0</totalCountValidation>
        </sourceList>
        <sourceList xmlns:xsi="http://www.w3.org/2001/XMLSchema-instance" xsi:type="termType">
            <count>2947</count>
            <expandedForm>has relationship other than synonymous, narrower, or broader/Concentration strength denominator value of</expandedForm>
            <termType>RO/concentration_strength_denominator_value_of</termType>
            <totalCountValidation>0</totalCountValidation>
        </sourceList>
        <sourceList xmlns:xsi="http://www.w3.org/2001/XMLSchema-instance" xsi:type="termType">
            <count>2947</count>
            <expandedForm>has relationship other than synonymous, narrower, or broader/Concentration strength numerator value of</expandedForm>
            <termType>RO/concentration_strength_numerator_value_of</termType>
            <totalCountValidation>0</totalCountValidation>
        </sourceList>
        <sourceList xmlns:xsi="http://www.w3.org/2001/XMLSchema-instance" xsi:type="termType">
            <count>2947</count>
            <expandedForm>has relationship other than synonymous, narrower, or broader/Has concentration strength numerator value</expandedForm>
            <termType>RO/has_concentration_strength_numerator_value</termType>
            <totalCountValidation>0</totalCountValidation>
        </sourceList>
        <sourceList xmlns:xsi="http://www.w3.org/2001/XMLSchema-instance" xsi:type="termType">
            <count>2948</count>
            <expandedForm>has relationship other than synonymous, narrower, or broader/Has concentration strength numerator unit</expandedForm>
            <termType>RO/has_concentration_strength_numerator_unit</termType>
            <totalCountValidation>0</totalCountValidation>
        </sourceList>
        <sourceList xmlns:xsi="http://www.w3.org/2001/XMLSchema-instance" xsi:type="termType">
            <count>2948</count>
            <expandedForm>has relationship other than synonymous, narrower, or broader/Concentration strength denominator unit of</expandedForm>
            <termType>RO/concentration_strength_denominator_unit_of</termType>
            <totalCountValidation>0</totalCountValidation>
        </sourceList>
        <sourceList xmlns:xsi="http://www.w3.org/2001/XMLSchema-instance" xsi:type="termType">
            <count>2948</count>
            <expandedForm>has relationship other than synonymous, narrower, or broader/Has concentration strength denominator unit</expandedForm>
            <termType>RO/has_concentration_strength_denominator_unit</termType>
            <totalCountValidation>0</totalCountValidation>
        </sourceList>
        <sourceList xmlns:xsi="http://www.w3.org/2001/XMLSchema-instance" xsi:type="termType">
            <count>2948</count>
            <expandedForm>has relationship other than synonymous, narrower, or broader/Concentration strength numerator unit of</expandedForm>
            <termType>RO/concentration_strength_numerator_unit_of</termType>
            <totalCountValidation>0</totalCountValidation>
        </sourceList>
        <sourceList xmlns:xsi="http://www.w3.org/2001/XMLSchema-instance" xsi:type="termType">
            <count>3123</count>
            <expandedForm>has relationship other than synonymous, narrower, or broader/Approach of</expandedForm>
            <termType>RO/approach_of</termType>
            <totalCountValidation>0</totalCountValidation>
        </sourceList>
        <sourceList xmlns:xsi="http://www.w3.org/2001/XMLSchema-instance" xsi:type="termType">
            <count>3123</count>
            <expandedForm>has relationship other than synonymous, narrower, or broader/Has approach</expandedForm>
            <termType>RO/has_approach</termType>
            <totalCountValidation>0</totalCountValidation>
        </sourceList>
        <sourceList xmlns:xsi="http://www.w3.org/2001/XMLSchema-instance" xsi:type="termType">
            <count>3257</count>
            <expandedForm>has relationship other than synonymous, narrower, or broader/Uses access device</expandedForm>
            <termType>RO/uses_access_device</termType>
            <totalCountValidation>0</totalCountValidation>
        </sourceList>
        <sourceList xmlns:xsi="http://www.w3.org/2001/XMLSchema-instance" xsi:type="termType">
            <count>3257</count>
            <expandedForm>has relationship other than synonymous, narrower, or broader/Access device used by</expandedForm>
            <termType>RO/access_device_used_by</termType>
            <totalCountValidation>0</totalCountValidation>
        </sourceList>
        <sourceList xmlns:xsi="http://www.w3.org/2001/XMLSchema-instance" xsi:type="termType">
            <count>3334</count>
            <expandedForm>has relationship other than synonymous, narrower, or broader/Has specimen source topography</expandedForm>
            <termType>RO/has_specimen_source_topography</termType>
            <totalCountValidation>0</totalCountValidation>
        </sourceList>
        <sourceList xmlns:xsi="http://www.w3.org/2001/XMLSchema-instance" xsi:type="termType">
            <count>3334</count>
            <expandedForm>has relationship other than synonymous, narrower, or broader/specimen source topography of</expandedForm>
            <termType>RO/specimen_source_topography_of</termType>
            <totalCountValidation>0</totalCountValidation>
        </sourceList>
        <sourceList xmlns:xsi="http://www.w3.org/2001/XMLSchema-instance" xsi:type="termType">
            <count>3410</count>
            <expandedForm>has relationship other than synonymous, narrower, or broader/Access instrument of</expandedForm>
            <termType>RO/access_instrument_of</termType>
            <totalCountValidation>0</totalCountValidation>
        </sourceList>
        <sourceList xmlns:xsi="http://www.w3.org/2001/XMLSchema-instance" xsi:type="termType">
            <count>3410</count>
            <expandedForm>has relationship other than synonymous, narrower, or broader/Has access instrument</expandedForm>
            <termType>RO/has_access_instrument</termType>
            <totalCountValidation>0</totalCountValidation>
        </sourceList>
        <sourceList xmlns:xsi="http://www.w3.org/2001/XMLSchema-instance" xsi:type="termType">
            <count>3778</count>
            <expandedForm>has relationship other than synonymous, narrower, or broader/Temporally follows</expandedForm>
            <termType>RO/temporally_follows</termType>
            <totalCountValidation>0</totalCountValidation>
        </sourceList>
        <sourceList xmlns:xsi="http://www.w3.org/2001/XMLSchema-instance" xsi:type="termType">
            <count>3778</count>
            <expandedForm>has relationship other than synonymous, narrower, or broader/Temporally followed by</expandedForm>
            <termType>RO/temporally_followed_by</termType>
            <totalCountValidation>0</totalCountValidation>
        </sourceList>
        <sourceList xmlns:xsi="http://www.w3.org/2001/XMLSchema-instance" xsi:type="termType">
            <count>4095</count>
            <expandedForm>has relationship other than synonymous, narrower, or broader/Revision status of</expandedForm>
            <termType>RO/revision_status_of</termType>
            <totalCountValidation>0</totalCountValidation>
        </sourceList>
        <sourceList xmlns:xsi="http://www.w3.org/2001/XMLSchema-instance" xsi:type="termType">
            <count>4095</count>
            <expandedForm>has relationship other than synonymous, narrower, or broader/Has revision status</expandedForm>
            <termType>RO/has_revision_status</termType>
            <totalCountValidation>0</totalCountValidation>
        </sourceList>
        <sourceList xmlns:xsi="http://www.w3.org/2001/XMLSchema-instance" xsi:type="termType">
            <count>4124</count>
            <expandedForm>has relationship other than synonymous, narrower, or broader/Specimen of</expandedForm>
            <termType>RO/specimen_of</termType>
            <totalCountValidation>0</totalCountValidation>
        </sourceList>
        <sourceList xmlns:xsi="http://www.w3.org/2001/XMLSchema-instance" xsi:type="termType">
            <count>4124</count>
            <expandedForm>has relationship other than synonymous, narrower, or broader/Has specimen</expandedForm>
            <termType>RO/has_specimen</termType>
            <totalCountValidation>0</totalCountValidation>
        </sourceList>
        <sourceList xmlns:xsi="http://www.w3.org/2001/XMLSchema-instance" xsi:type="termType">
            <count>4365</count>
            <expandedForm>source asserted synonymy./Plain text form of, Metathesaurus-asserted</expandedForm>
            <termType>SY/mth_plain_text_form_of</termType>
            <totalCountValidation>0</totalCountValidation>
        </sourceList>
        <sourceList xmlns:xsi="http://www.w3.org/2001/XMLSchema-instance" xsi:type="termType">
            <count>4365</count>
            <expandedForm>source asserted synonymy./Has XML form, Metathesaurus-asserted</expandedForm>
            <termType>SY/mth_has_xml_form</termType>
            <totalCountValidation>0</totalCountValidation>
        </sourceList>
        <sourceList xmlns:xsi="http://www.w3.org/2001/XMLSchema-instance" xsi:type="termType">
            <count>4365</count>
            <expandedForm>source asserted synonymy./XML form of, Metathesaurus-asserted</expandedForm>
            <termType>SY/mth_xml_form_of</termType>
            <totalCountValidation>0</totalCountValidation>
        </sourceList>
        <sourceList xmlns:xsi="http://www.w3.org/2001/XMLSchema-instance" xsi:type="termType">
            <count>4365</count>
            <expandedForm>source asserted synonymy./Has plain text form, Metathesaurus-asserted</expandedForm>
            <termType>SY/mth_has_plain_text_form</termType>
            <totalCountValidation>0</totalCountValidation>
        </sourceList>
        <sourceList xmlns:xsi="http://www.w3.org/2001/XMLSchema-instance" xsi:type="termType">
            <count>4808</count>
            <expandedForm>has relationship other than synonymous, narrower, or broader/Course of</expandedForm>
            <termType>RO/course_of</termType>
            <totalCountValidation>0</totalCountValidation>
        </sourceList>
        <sourceList xmlns:xsi="http://www.w3.org/2001/XMLSchema-instance" xsi:type="termType">
            <count>4808</count>
            <expandedForm>has relationship other than synonymous, narrower, or broader/Has course</expandedForm>
            <termType>RO/has_course</termType>
            <totalCountValidation>0</totalCountValidation>
        </sourceList>
        <sourceList xmlns:xsi="http://www.w3.org/2001/XMLSchema-instance" xsi:type="termType">
            <count>4976</count>
            <expandedForm>has relationship other than synonymous, narrower, or broader/Unit of presentation of</expandedForm>
            <termType>RO/unit_of_presentation_of</termType>
            <totalCountValidation>0</totalCountValidation>
        </sourceList>
        <sourceList xmlns:xsi="http://www.w3.org/2001/XMLSchema-instance" xsi:type="termType">
            <count>4976</count>
            <expandedForm>has relationship other than synonymous, narrower, or broader/Has unit of presentation</expandedForm>
            <termType>RO/has_unit_of_presentation</termType>
            <totalCountValidation>0</totalCountValidation>
        </sourceList>
        <sourceList xmlns:xsi="http://www.w3.org/2001/XMLSchema-instance" xsi:type="termType">
            <count>5212</count>
            <expandedForm>has relationship other than synonymous, narrower, or broader/Clinical course of</expandedForm>
            <termType>RO/clinical_course_of</termType>
            <totalCountValidation>0</totalCountValidation>
        </sourceList>
        <sourceList xmlns:xsi="http://www.w3.org/2001/XMLSchema-instance" xsi:type="termType">
            <count>5212</count>
            <expandedForm>has relationship other than synonymous, narrower, or broader/Has clinical course</expandedForm>
            <termType>RO/has_clinical_course</termType>
            <totalCountValidation>0</totalCountValidation>
        </sourceList>
        <sourceList xmlns:xsi="http://www.w3.org/2001/XMLSchema-instance" xsi:type="termType">
            <count>5795</count>
            <expandedForm>has relationship other than synonymous, narrower, or broader/Has procedure context</expandedForm>
            <termType>RO/has_procedure_context</termType>
            <totalCountValidation>0</totalCountValidation>
        </sourceList>
        <sourceList xmlns:xsi="http://www.w3.org/2001/XMLSchema-instance" xsi:type="termType">
            <count>5795</count>
            <expandedForm>has relationship other than synonymous, narrower, or broader/Procedure context of</expandedForm>
            <termType>RO/procedure_context_of</termType>
            <totalCountValidation>0</totalCountValidation>
        </sourceList>
        <sourceList xmlns:xsi="http://www.w3.org/2001/XMLSchema-instance" xsi:type="termType">
            <count>5796</count>
            <expandedForm>has relationship other than synonymous, narrower, or broader/Presentation strength denominator value of</expandedForm>
            <termType>RO/presentation_strength_denominator_value_of</termType>
            <totalCountValidation>0</totalCountValidation>
        </sourceList>
        <sourceList xmlns:xsi="http://www.w3.org/2001/XMLSchema-instance" xsi:type="termType">
            <count>5796</count>
            <expandedForm>has relationship other than synonymous, narrower, or broader/Has presentation strength denominator value</expandedForm>
            <termType>RO/has_presentation_strength_denominator_value</termType>
            <totalCountValidation>0</totalCountValidation>
        </sourceList>
        <sourceList xmlns:xsi="http://www.w3.org/2001/XMLSchema-instance" xsi:type="termType">
            <count>5797</count>
            <expandedForm>has relationship other than synonymous, narrower, or broader/Presentation strength denominator unit of</expandedForm>
            <termType>RO/presentation_strength_denominator_unit_of</termType>
            <totalCountValidation>0</totalCountValidation>
        </sourceList>
        <sourceList xmlns:xsi="http://www.w3.org/2001/XMLSchema-instance" xsi:type="termType">
            <count>5797</count>
            <expandedForm>has relationship other than synonymous, narrower, or broader/Has presentation strength denominator unit</expandedForm>
            <termType>RO/has_presentation_strength_denominator_unit</termType>
            <totalCountValidation>0</totalCountValidation>
        </sourceList>
        <sourceList xmlns:xsi="http://www.w3.org/2001/XMLSchema-instance" xsi:type="termType">
            <count>5882</count>
            <expandedForm>has relationship other than synonymous, narrower, or broader/Associated procedure of</expandedForm>
            <termType>RO/associated_procedure_of</termType>
            <totalCountValidation>0</totalCountValidation>
        </sourceList>
        <sourceList xmlns:xsi="http://www.w3.org/2001/XMLSchema-instance" xsi:type="termType">
            <count>5882</count>
            <expandedForm>has relationship other than synonymous, narrower, or broader/Has associated procedure</expandedForm>
            <termType>RO/has_associated_procedure</termType>
            <totalCountValidation>0</totalCountValidation>
        </sourceList>
        <sourceList xmlns:xsi="http://www.w3.org/2001/XMLSchema-instance" xsi:type="termType">
            <count>6034</count>
            <expandedForm>has relationship other than synonymous, narrower, or broader/Presentation strength numerator unit of</expandedForm>
            <termType>RO/presentation_strength_numerator_unit_of</termType>
            <totalCountValidation>0</totalCountValidation>
        </sourceList>
        <sourceList xmlns:xsi="http://www.w3.org/2001/XMLSchema-instance" xsi:type="termType">
            <count>6034</count>
            <expandedForm>has relationship other than synonymous, narrower, or broader/Has presentation strength numerator unit</expandedForm>
            <termType>RO/has_presentation_strength_numerator_unit</termType>
            <totalCountValidation>0</totalCountValidation>
        </sourceList>
        <sourceList xmlns:xsi="http://www.w3.org/2001/XMLSchema-instance" xsi:type="termType">
            <count>6305</count>
            <expandedForm>has relationship other than synonymous, narrower, or broader/measured_component_of</expandedForm>
            <termType>RO/measured_component_of</termType>
            <totalCountValidation>0</totalCountValidation>
        </sourceList>
        <sourceList xmlns:xsi="http://www.w3.org/2001/XMLSchema-instance" xsi:type="termType">
            <count>6305</count>
            <expandedForm>has relationship other than synonymous, narrower, or broader/has_measured_component</expandedForm>
            <termType>RO/has_measured_component</termType>
            <totalCountValidation>0</totalCountValidation>
        </sourceList>
        <sourceList xmlns:xsi="http://www.w3.org/2001/XMLSchema-instance" xsi:type="termType">
            <count>6467</count>
            <expandedForm>has relationship other than synonymous, narrower, or broader/Has presentation strength numerator value</expandedForm>
            <termType>RO/has_presentation_strength_numerator_value</termType>
            <totalCountValidation>0</totalCountValidation>
        </sourceList>
        <sourceList xmlns:xsi="http://www.w3.org/2001/XMLSchema-instance" xsi:type="termType">
            <count>6467</count>
            <expandedForm>has relationship other than synonymous, narrower, or broader/Presentation strength numerator value of</expandedForm>
            <termType>RO/presentation_strength_numerator_value_of</termType>
            <totalCountValidation>0</totalCountValidation>
        </sourceList>
        <sourceList xmlns:xsi="http://www.w3.org/2001/XMLSchema-instance" xsi:type="termType">
            <count>6712</count>
            <expandedForm>has relationship other than synonymous, narrower, or broader/Focus of</expandedForm>
            <termType>RO/focus_of</termType>
            <totalCountValidation>0</totalCountValidation>
        </sourceList>
        <sourceList xmlns:xsi="http://www.w3.org/2001/XMLSchema-instance" xsi:type="termType">
            <count>6712</count>
            <expandedForm>has relationship other than synonymous, narrower, or broader/Has focus</expandedForm>
            <termType>RO/has_focus</termType>
            <totalCountValidation>0</totalCountValidation>
        </sourceList>
        <sourceList xmlns:xsi="http://www.w3.org/2001/XMLSchema-instance" xsi:type="termType">
            <count>6839</count>
            <expandedForm>has relationship other than synonymous, narrower, or broader/Uses substance</expandedForm>
            <termType>RO/uses_substance</termType>
            <totalCountValidation>0</totalCountValidation>
        </sourceList>
        <sourceList xmlns:xsi="http://www.w3.org/2001/XMLSchema-instance" xsi:type="termType">
            <count>6839</count>
            <expandedForm>has relationship other than synonymous, narrower, or broader/Substance used by</expandedForm>
            <termType>RO/substance_used_by</termType>
            <totalCountValidation>0</totalCountValidation>
        </sourceList>
        <sourceList xmlns:xsi="http://www.w3.org/2001/XMLSchema-instance" xsi:type="termType">
            <count>7533</count>
            <expandedForm>has relationship other than synonymous, narrower, or broader/Occurs before</expandedForm>
            <termType>RO/occurs_before</termType>
            <totalCountValidation>0</totalCountValidation>
        </sourceList>
        <sourceList xmlns:xsi="http://www.w3.org/2001/XMLSchema-instance" xsi:type="termType">
            <count>7533</count>
            <expandedForm>has relationship other than synonymous, narrower, or broader/Occurs after</expandedForm>
            <termType>RO/occurs_after</termType>
            <totalCountValidation>0</totalCountValidation>
        </sourceList>
        <sourceList xmlns:xsi="http://www.w3.org/2001/XMLSchema-instance" xsi:type="termType">
            <count>7642</count>
            <expandedForm>has relationship other than synonymous, narrower, or broader/Used by</expandedForm>
            <termType>RO/used_by</termType>
            <totalCountValidation>0</totalCountValidation>
        </sourceList>
        <sourceList xmlns:xsi="http://www.w3.org/2001/XMLSchema-instance" xsi:type="termType">
            <count>7642</count>
            <expandedForm>has relationship other than synonymous, narrower, or broader/Uses</expandedForm>
            <termType>RO/uses</termType>
            <totalCountValidation>0</totalCountValidation>
        </sourceList>
        <sourceList xmlns:xsi="http://www.w3.org/2001/XMLSchema-instance" xsi:type="termType">
            <count>8114</count>
            <expandedForm>has relationship other than synonymous, narrower, or broader/Has precise active ingredient</expandedForm>
            <termType>RO/has_precise_active_ingredient</termType>
            <totalCountValidation>0</totalCountValidation>
        </sourceList>
        <sourceList xmlns:xsi="http://www.w3.org/2001/XMLSchema-instance" xsi:type="termType">
            <count>8114</count>
            <expandedForm>has relationship other than synonymous, narrower, or broader/Precise active ingredient of</expandedForm>
            <termType>RO/precise_active_ingredient_of</termType>
            <totalCountValidation>0</totalCountValidation>
        </sourceList>
        <sourceList xmlns:xsi="http://www.w3.org/2001/XMLSchema-instance" xsi:type="termType">
            <count>8675</count>
            <expandedForm>has relationship other than synonymous, narrower, or broader/Has basis of strength substance</expandedForm>
            <termType>RO/has_basis_of_strength_substance</termType>
            <totalCountValidation>0</totalCountValidation>
        </sourceList>
        <sourceList xmlns:xsi="http://www.w3.org/2001/XMLSchema-instance" xsi:type="termType">
            <count>8675</count>
            <expandedForm>has relationship other than synonymous, narrower, or broader/Basis of strength substance of</expandedForm>
            <termType>RO/basis_of_strength_substance_of</termType>
            <totalCountValidation>0</totalCountValidation>
        </sourceList>
        <sourceList xmlns:xsi="http://www.w3.org/2001/XMLSchema-instance" xsi:type="termType">
            <count>9113</count>
            <expandedForm>has relationship other than synonymous, narrower, or broader/Has finding method</expandedForm>
            <termType>RO/has_finding_method</termType>
            <totalCountValidation>0</totalCountValidation>
        </sourceList>
        <sourceList xmlns:xsi="http://www.w3.org/2001/XMLSchema-instance" xsi:type="termType">
            <count>9113</count>
            <expandedForm>has relationship other than synonymous, narrower, or broader/Finding method of</expandedForm>
            <termType>RO/finding_method_of</termType>
            <totalCountValidation>0</totalCountValidation>
        </sourceList>
        <sourceList xmlns:xsi="http://www.w3.org/2001/XMLSchema-instance" xsi:type="termType">
            <count>9212</count>
            <expandedForm>has relationship other than synonymous, narrower, or broader/Associated with</expandedForm>
            <termType>RO/associated_with</termType>
            <totalCountValidation>0</totalCountValidation>
        </sourceList>
        <sourceList xmlns:xsi="http://www.w3.org/2001/XMLSchema-instance" xsi:type="termType">
            <count>9402</count>
            <expandedForm>has relationship other than synonymous, narrower, or broader/Disposition of</expandedForm>
            <termType>RO/disposition_of</termType>
            <totalCountValidation>0</totalCountValidation>
        </sourceList>
        <sourceList xmlns:xsi="http://www.w3.org/2001/XMLSchema-instance" xsi:type="termType">
            <count>9402</count>
            <expandedForm>has relationship other than synonymous, narrower, or broader/Has disposition</expandedForm>
            <termType>RO/has_disposition</termType>
            <totalCountValidation>0</totalCountValidation>
        </sourceList>
        <sourceList xmlns:xsi="http://www.w3.org/2001/XMLSchema-instance" xsi:type="termType">
            <count>9467</count>
            <expandedForm>has relationship other than synonymous, narrower, or broader/Cause of</expandedForm>
            <termType>RO/cause_of</termType>
            <totalCountValidation>0</totalCountValidation>
        </sourceList>
        <sourceList xmlns:xsi="http://www.w3.org/2001/XMLSchema-instance" xsi:type="termType">
            <count>9467</count>
            <expandedForm>has relationship other than synonymous, narrower, or broader/Due to</expandedForm>
            <termType>RO/due_to</termType>
            <totalCountValidation>0</totalCountValidation>
        </sourceList>
        <sourceList xmlns:xsi="http://www.w3.org/2001/XMLSchema-instance" xsi:type="termType">
            <count>9500</count>
            <expandedForm>has relationship other than synonymous, narrower, or broader/Access of</expandedForm>
            <termType>RO/access_of</termType>
            <totalCountValidation>0</totalCountValidation>
        </sourceList>
        <sourceList xmlns:xsi="http://www.w3.org/2001/XMLSchema-instance" xsi:type="termType">
            <count>9500</count>
            <expandedForm>has relationship other than synonymous, narrower, or broader/Has access</expandedForm>
            <termType>RO/has_access</termType>
            <totalCountValidation>0</totalCountValidation>
        </sourceList>
        <sourceList xmlns:xsi="http://www.w3.org/2001/XMLSchema-instance" xsi:type="termType">
            <count>9968</count>
            <expandedForm>has relationship other than synonymous, narrower, or broader/Replaces</expandedForm>
            <termType>RO/replaces</termType>
            <totalCountValidation>0</totalCountValidation>
        </sourceList>
        <sourceList xmlns:xsi="http://www.w3.org/2001/XMLSchema-instance" xsi:type="termType">
            <count>9968</count>
            <expandedForm>has relationship other than synonymous, narrower, or broader/Replaced by</expandedForm>
            <termType>RO/replaced_by</termType>
            <totalCountValidation>0</totalCountValidation>
        </sourceList>
        <sourceList xmlns:xsi="http://www.w3.org/2001/XMLSchema-instance" xsi:type="termType">
            <count>10353</count>
            <expandedForm>has relationship other than synonymous, narrower, or broader/Has laterality</expandedForm>
            <termType>RO/has_laterality</termType>
            <totalCountValidation>0</totalCountValidation>
        </sourceList>
        <sourceList xmlns:xsi="http://www.w3.org/2001/XMLSchema-instance" xsi:type="termType">
            <count>10353</count>
            <expandedForm>has relationship other than synonymous, narrower, or broader/Laterality of</expandedForm>
            <termType>RO/laterality_of</termType>
            <totalCountValidation>0</totalCountValidation>
        </sourceList>
        <sourceList xmlns:xsi="http://www.w3.org/2001/XMLSchema-instance" xsi:type="termType">
            <count>10929</count>
            <expandedForm>has relationship other than synonymous, narrower, or broader/Definitional manifestation of</expandedForm>
            <termType>RO/definitional_manifestation_of</termType>
            <totalCountValidation>0</totalCountValidation>
        </sourceList>
        <sourceList xmlns:xsi="http://www.w3.org/2001/XMLSchema-instance" xsi:type="termType">
            <count>10929</count>
            <expandedForm>has relationship other than synonymous, narrower, or broader/Has definitional manifestation</expandedForm>
            <termType>RO/has_definitional_manifestation</termType>
            <totalCountValidation>0</totalCountValidation>
        </sourceList>
        <sourceList xmlns:xsi="http://www.w3.org/2001/XMLSchema-instance" xsi:type="termType">
            <count>11057</count>
            <expandedForm>has relationship other than synonymous, narrower, or broader/Device used by</expandedForm>
            <termType>RO/device_used_by</termType>
            <totalCountValidation>0</totalCountValidation>
        </sourceList>
        <sourceList xmlns:xsi="http://www.w3.org/2001/XMLSchema-instance" xsi:type="termType">
            <count>11057</count>
            <expandedForm>has relationship other than synonymous, narrower, or broader/Uses device</expandedForm>
            <termType>RO/uses_device</termType>
            <totalCountValidation>0</totalCountValidation>
        </sourceList>
        <sourceList xmlns:xsi="http://www.w3.org/2001/XMLSchema-instance" xsi:type="termType">
            <count>11378</count>
            <expandedForm>has relationship other than synonymous, narrower, or broader/Finding context of</expandedForm>
            <termType>RO/finding_context_of</termType>
            <totalCountValidation>0</totalCountValidation>
        </sourceList>
        <sourceList xmlns:xsi="http://www.w3.org/2001/XMLSchema-instance" xsi:type="termType">
            <count>11378</count>
            <expandedForm>has relationship other than synonymous, narrower, or broader/Has finding context</expandedForm>
            <termType>RO/has_finding_context</termType>
            <totalCountValidation>0</totalCountValidation>
        </sourceList>
        <sourceList xmlns:xsi="http://www.w3.org/2001/XMLSchema-instance" xsi:type="termType">
            <count>12685</count>
            <expandedForm>has relationship other than synonymous, narrower, or broader/Associated finding of</expandedForm>
            <termType>RO/associated_finding_of</termType>
            <totalCountValidation>0</totalCountValidation>
        </sourceList>
        <sourceList xmlns:xsi="http://www.w3.org/2001/XMLSchema-instance" xsi:type="termType">
            <count>12685</count>
            <expandedForm>has relationship other than synonymous, narrower, or broader/Has associated finding</expandedForm>
            <termType>RO/has_associated_finding</termType>
            <totalCountValidation>0</totalCountValidation>
        </sourceList>
        <sourceList xmlns:xsi="http://www.w3.org/2001/XMLSchema-instance" xsi:type="termType">
            <count>13980</count>
            <expandedForm>has relationship other than synonymous, narrower, or broader/Count of base of active ingredient of</expandedForm>
            <termType>RO/count_of_base_of_active_ingredient_of</termType>
            <totalCountValidation>0</totalCountValidation>
        </sourceList>
        <sourceList xmlns:xsi="http://www.w3.org/2001/XMLSchema-instance" xsi:type="termType">
            <count>13980</count>
            <expandedForm>has relationship other than synonymous, narrower, or broader/Has count of base of active ingredient</expandedForm>
            <termType>RO/has_count_of_base_of_active_ingredient</termType>
            <totalCountValidation>0</totalCountValidation>
        </sourceList>
        <sourceList xmlns:xsi="http://www.w3.org/2001/XMLSchema-instance" xsi:type="termType">
            <count>14305</count>
            <expandedForm>has relationship other than synonymous, narrower, or broader/Entire anatomy structure of</expandedForm>
            <termType>RO/entire_anatomy_structure_of</termType>
            <totalCountValidation>0</totalCountValidation>
        </sourceList>
        <sourceList xmlns:xsi="http://www.w3.org/2001/XMLSchema-instance" xsi:type="termType">
            <count>14305</count>
            <expandedForm>has relationship other than synonymous, narrower, or broader/Has entire anatomy structure</expandedForm>
            <termType>RO/has_entire_anatomy_structure</termType>
            <totalCountValidation>0</totalCountValidation>
        </sourceList>
        <sourceList xmlns:xsi="http://www.w3.org/2001/XMLSchema-instance" xsi:type="termType">
            <count>16825</count>
            <expandedForm>has relationship other than synonymous, narrower, or broader/Component of</expandedForm>
            <termType>RO/component_of</termType>
            <totalCountValidation>0</totalCountValidation>
        </sourceList>
        <sourceList xmlns:xsi="http://www.w3.org/2001/XMLSchema-instance" xsi:type="termType">
            <count>16825</count>
            <expandedForm>has relationship other than synonymous, narrower, or broader/Has component</expandedForm>
            <termType>RO/has_component</termType>
            <totalCountValidation>0</totalCountValidation>
        </sourceList>
        <sourceList xmlns:xsi="http://www.w3.org/2001/XMLSchema-instance" xsi:type="termType">
            <count>16893</count>
            <expandedForm>has relationship other than synonymous, narrower, or broader/Subject relationship context of</expandedForm>
            <termType>RO/subject_relationship_context_of</termType>
            <totalCountValidation>0</totalCountValidation>
        </sourceList>
        <sourceList xmlns:xsi="http://www.w3.org/2001/XMLSchema-instance" xsi:type="termType">
            <count>16893</count>
            <expandedForm>has relationship other than synonymous, narrower, or broader/Has subject relationship context</expandedForm>
            <termType>RO/has_subject_relationship_context</termType>
            <totalCountValidation>0</totalCountValidation>
        </sourceList>
        <sourceList xmlns:xsi="http://www.w3.org/2001/XMLSchema-instance" xsi:type="termType">
            <count>17157</count>
            <expandedForm>has relationship other than synonymous, narrower, or broader/Temporal context of</expandedForm>
            <termType>RO/temporal_context_of</termType>
            <totalCountValidation>0</totalCountValidation>
        </sourceList>
        <sourceList xmlns:xsi="http://www.w3.org/2001/XMLSchema-instance" xsi:type="termType">
            <count>17157</count>
            <expandedForm>has relationship other than synonymous, narrower, or broader/Has temporal context</expandedForm>
            <termType>RO/has_temporal_context</termType>
            <totalCountValidation>0</totalCountValidation>
        </sourceList>
        <sourceList xmlns:xsi="http://www.w3.org/2001/XMLSchema-instance" xsi:type="termType">
            <count>17396</count>
            <expandedForm>has relationship other than synonymous, narrower, or broader/Moved to</expandedForm>
            <termType>RO/moved_to</termType>
            <totalCountValidation>0</totalCountValidation>
        </sourceList>
        <sourceList xmlns:xsi="http://www.w3.org/2001/XMLSchema-instance" xsi:type="termType">
            <count>17396</count>
            <expandedForm>has relationship other than synonymous, narrower, or broader/Moved from</expandedForm>
            <termType>RO/moved_from</termType>
            <totalCountValidation>0</totalCountValidation>
        </sourceList>
        <sourceList xmlns:xsi="http://www.w3.org/2001/XMLSchema-instance" xsi:type="termType">
            <count>17686</count>
            <expandedForm>has relationship other than synonymous, narrower, or broader/Has direct device</expandedForm>
            <termType>RO/has_direct_device</termType>
            <totalCountValidation>0</totalCountValidation>
        </sourceList>
        <sourceList xmlns:xsi="http://www.w3.org/2001/XMLSchema-instance" xsi:type="termType">
            <count>17686</count>
            <expandedForm>has relationship other than synonymous, narrower, or broader/Direct device of</expandedForm>
            <termType>RO/direct_device_of</termType>
            <totalCountValidation>0</totalCountValidation>
        </sourceList>
        <sourceList xmlns:xsi="http://www.w3.org/2001/XMLSchema-instance" xsi:type="termType">
            <count>22638</count>
            <expandedForm>has a broader relationship/Inverse was a</expandedForm>
            <termType>RB/inverse_was_a</termType>
            <totalCountValidation>0</totalCountValidation>
        </sourceList>
        <sourceList xmlns:xsi="http://www.w3.org/2001/XMLSchema-instance" xsi:type="termType">
            <count>22638</count>
            <expandedForm>has a narrower relationship/Was a</expandedForm>
            <termType>RN/was_a</termType>
            <totalCountValidation>0</totalCountValidation>
        </sourceList>
        <sourceList xmlns:xsi="http://www.w3.org/2001/XMLSchema-instance" xsi:type="termType">
            <count>22955</count>
            <expandedForm>has relationship other than synonymous, narrower, or broader/Has direct substance</expandedForm>
            <termType>RO/has_direct_substance</termType>
            <totalCountValidation>0</totalCountValidation>
        </sourceList>
        <sourceList xmlns:xsi="http://www.w3.org/2001/XMLSchema-instance" xsi:type="termType">
            <count>22955</count>
            <expandedForm>has relationship other than synonymous, narrower, or broader/Direct substance of</expandedForm>
            <termType>RO/direct_substance_of</termType>
            <totalCountValidation>0</totalCountValidation>
        </sourceList>
        <sourceList xmlns:xsi="http://www.w3.org/2001/XMLSchema-instance" xsi:type="termType">
            <count>23860</count>
            <expandedForm>has relationship other than synonymous, narrower, or broader/Interpretation of</expandedForm>
            <termType>RO/interpretation_of</termType>
            <totalCountValidation>0</totalCountValidation>
        </sourceList>
        <sourceList xmlns:xsi="http://www.w3.org/2001/XMLSchema-instance" xsi:type="termType">
            <count>23860</count>
            <expandedForm>has relationship other than synonymous, narrower, or broader/Has interpretation</expandedForm>
            <termType>RO/has_interpretation</termType>
            <totalCountValidation>0</totalCountValidation>
        </sourceList>
        <sourceList xmlns:xsi="http://www.w3.org/2001/XMLSchema-instance" xsi:type="termType">
            <count>25852</count>
            <expandedForm>has relationship other than synonymous, narrower, or broader/Has intent</expandedForm>
            <termType>RO/has_intent</termType>
            <totalCountValidation>0</totalCountValidation>
        </sourceList>
        <sourceList xmlns:xsi="http://www.w3.org/2001/XMLSchema-instance" xsi:type="termType">
            <count>25852</count>
            <expandedForm>has relationship other than synonymous, narrower, or broader/Intent of</expandedForm>
            <termType>RO/intent_of</termType>
            <totalCountValidation>0</totalCountValidation>
        </sourceList>
        <sourceList xmlns:xsi="http://www.w3.org/2001/XMLSchema-instance" xsi:type="termType">
            <count>27049</count>
            <expandedForm>has relationship other than synonymous, narrower, or broader/Has indirect procedure site</expandedForm>
            <termType>RO/has_indirect_procedure_site</termType>
            <totalCountValidation>0</totalCountValidation>
        </sourceList>
        <sourceList xmlns:xsi="http://www.w3.org/2001/XMLSchema-instance" xsi:type="termType">
            <count>27049</count>
            <expandedForm>has relationship other than synonymous, narrower, or broader/Indirect procedure site of</expandedForm>
            <termType>RO/indirect_procedure_site_of</termType>
            <totalCountValidation>0</totalCountValidation>
        </sourceList>
        <sourceList xmlns:xsi="http://www.w3.org/2001/XMLSchema-instance" xsi:type="termType">
            <count>29596</count>
            <expandedForm>has relationship other than synonymous, narrower, or broader/Has direct morphology</expandedForm>
            <termType>RO/has_direct_morphology</termType>
            <totalCountValidation>0</totalCountValidation>
        </sourceList>
        <sourceList xmlns:xsi="http://www.w3.org/2001/XMLSchema-instance" xsi:type="termType">
            <count>29596</count>
            <expandedForm>has relationship other than synonymous, narrower, or broader/Direct morphology of</expandedForm>
            <termType>RO/direct_morphology_of</termType>
            <totalCountValidation>0</totalCountValidation>
        </sourceList>
        <sourceList xmlns:xsi="http://www.w3.org/2001/XMLSchema-instance" xsi:type="termType">
            <count>30807</count>
            <expandedForm>has relationship other than synonymous, narrower, or broader/Has dose form</expandedForm>
            <termType>RO/has_dose_form</termType>
            <totalCountValidation>0</totalCountValidation>
        </sourceList>
        <sourceList xmlns:xsi="http://www.w3.org/2001/XMLSchema-instance" xsi:type="termType">
            <count>30807</count>
            <expandedForm>has relationship other than synonymous, narrower, or broader/Dose form of</expandedForm>
            <termType>RO/dose_form_of</termType>
            <totalCountValidation>0</totalCountValidation>
        </sourceList>
        <sourceList xmlns:xsi="http://www.w3.org/2001/XMLSchema-instance" xsi:type="termType">
            <count>39275</count>
            <expandedForm>has relationship other than synonymous, narrower, or broader/Has occurrence</expandedForm>
            <termType>RO/has_occurrence</termType>
            <totalCountValidation>0</totalCountValidation>
        </sourceList>
        <sourceList xmlns:xsi="http://www.w3.org/2001/XMLSchema-instance" xsi:type="termType">
            <count>39275</count>
            <expandedForm>has relationship other than synonymous, narrower, or broader/Occurs in</expandedForm>
            <termType>RO/occurs_in</termType>
            <totalCountValidation>0</totalCountValidation>
        </sourceList>
        <sourceList xmlns:xsi="http://www.w3.org/2001/XMLSchema-instance" xsi:type="termType">
            <count>52974</count>
            <expandedForm>has relationship other than synonymous, narrower, or broader/Pathological process of</expandedForm>
            <termType>RO/pathological_process_of</termType>
            <totalCountValidation>0</totalCountValidation>
        </sourceList>
        <sourceList xmlns:xsi="http://www.w3.org/2001/XMLSchema-instance" xsi:type="termType">
            <count>52974</count>
            <expandedForm>has relationship other than synonymous, narrower, or broader/Has pathological process</expandedForm>
            <termType>RO/has_pathological_process</termType>
            <totalCountValidation>0</totalCountValidation>
        </sourceList>
        <sourceList xmlns:xsi="http://www.w3.org/2001/XMLSchema-instance" xsi:type="termType">
            <count>53710</count>
            <expandedForm>has a narrower relationship/Part of</expandedForm>
            <termType>RN/part_of</termType>
            <totalCountValidation>0</totalCountValidation>
        </sourceList>
        <sourceList xmlns:xsi="http://www.w3.org/2001/XMLSchema-instance" xsi:type="termType">
            <count>53710</count>
            <expandedForm>has a broader relationship/Has part</expandedForm>
            <termType>RB/has_part</termType>
            <totalCountValidation>0</totalCountValidation>
        </sourceList>
        <sourceList xmlns:xsi="http://www.w3.org/2001/XMLSchema-instance" xsi:type="termType">
            <count>63501</count>
            <expandedForm>has relationship other than synonymous, narrower, or broader/Active ingredient of</expandedForm>
            <termType>RO/active_ingredient_of</termType>
            <totalCountValidation>0</totalCountValidation>
        </sourceList>
        <sourceList xmlns:xsi="http://www.w3.org/2001/XMLSchema-instance" xsi:type="termType">
            <count>63501</count>
            <expandedForm>has relationship other than synonymous, narrower, or broader/Has active ingredient</expandedForm>
            <termType>RO/has_active_ingredient</termType>
            <totalCountValidation>0</totalCountValidation>
        </sourceList>
        <sourceList xmlns:xsi="http://www.w3.org/2001/XMLSchema-instance" xsi:type="termType">
            <count>82232</count>
            <expandedForm>has relationship other than synonymous, narrower, or broader/Is interpreted by</expandedForm>
            <termType>RO/is_interpreted_by</termType>
            <totalCountValidation>0</totalCountValidation>
        </sourceList>
        <sourceList xmlns:xsi="http://www.w3.org/2001/XMLSchema-instance" xsi:type="termType">
            <count>82232</count>
            <expandedForm>has relationship other than synonymous, narrower, or broader/Interprets</expandedForm>
            <termType>RO/interprets</termType>
            <totalCountValidation>0</totalCountValidation>
        </sourceList>
        <sourceList xmlns:xsi="http://www.w3.org/2001/XMLSchema-instance" xsi:type="termType">
            <count>82783</count>
            <expandedForm>has relationship other than synonymous, narrower, or broader/Has direct procedure site</expandedForm>
            <termType>RO/has_direct_procedure_site</termType>
            <totalCountValidation>0</totalCountValidation>
        </sourceList>
        <sourceList xmlns:xsi="http://www.w3.org/2001/XMLSchema-instance" xsi:type="termType">
            <count>82783</count>
            <expandedForm>has relationship other than synonymous, narrower, or broader/Direct procedure site of</expandedForm>
            <termType>RO/direct_procedure_site_of</termType>
            <totalCountValidation>0</totalCountValidation>
        </sourceList>
        <sourceList xmlns:xsi="http://www.w3.org/2001/XMLSchema-instance" xsi:type="termType">
            <count>85745</count>
            <expandedForm>has relationship other than synonymous, narrower, or broader/Has causative agent</expandedForm>
            <termType>RO/has_causative_agent</termType>
            <totalCountValidation>0</totalCountValidation>
        </sourceList>
        <sourceList xmlns:xsi="http://www.w3.org/2001/XMLSchema-instance" xsi:type="termType">
            <count>85745</count>
            <expandedForm>has relationship other than synonymous, narrower, or broader/Causative agent of</expandedForm>
            <termType>RO/causative_agent_of</termType>
            <totalCountValidation>0</totalCountValidation>
        </sourceList>
        <sourceList xmlns:xsi="http://www.w3.org/2001/XMLSchema-instance" xsi:type="termType">
            <count>89162</count>
            <expandedForm>has relationship other than synonymous, narrower, or broader/Possibly equivalent to</expandedForm>
            <termType>RO/possibly_equivalent_to</termType>
            <totalCountValidation>0</totalCountValidation>
        </sourceList>
        <sourceList xmlns:xsi="http://www.w3.org/2001/XMLSchema-instance" xsi:type="termType">
            <count>103708</count>
            <expandedForm>source asserted synonymy./Same as</expandedForm>
            <termType>SY/same_as</termType>
            <totalCountValidation>0</totalCountValidation>
        </sourceList>
        <sourceList xmlns:xsi="http://www.w3.org/2001/XMLSchema-instance" xsi:type="termType">
            <count>129604</count>
            <expandedForm>has relationship other than synonymous, narrower, or broader/Procedure site of</expandedForm>
            <termType>RO/procedure_site_of</termType>
            <totalCountValidation>0</totalCountValidation>
        </sourceList>
        <sourceList xmlns:xsi="http://www.w3.org/2001/XMLSchema-instance" xsi:type="termType">
            <count>129604</count>
            <expandedForm>has relationship other than synonymous, narrower, or broader/Has procedure site</expandedForm>
            <termType>RO/has_procedure_site</termType>
            <totalCountValidation>0</totalCountValidation>
        </sourceList>
        <sourceList xmlns:xsi="http://www.w3.org/2001/XMLSchema-instance" xsi:type="termType">
            <count>138784</count>
            <expandedForm>has relationship other than synonymous, narrower, or broader/Mapped to</expandedForm>
            <termType>RO/mapped_to</termType>
            <totalCountValidation>0</totalCountValidation>
        </sourceList>
        <sourceList xmlns:xsi="http://www.w3.org/2001/XMLSchema-instance" xsi:type="termType">
            <count>138784</count>
            <expandedForm>has relationship other than synonymous, narrower, or broader/Mapped from</expandedForm>
            <termType>RO/mapped_from</termType>
            <totalCountValidation>0</totalCountValidation>
        </sourceList>
        <sourceList xmlns:xsi="http://www.w3.org/2001/XMLSchema-instance" xsi:type="termType">
            <count>260192</count>
            <expandedForm>has relationship other than synonymous, narrower, or broader/Has associated morphology</expandedForm>
            <termType>RO/has_associated_morphology</termType>
            <totalCountValidation>0</totalCountValidation>
        </sourceList>
        <sourceList xmlns:xsi="http://www.w3.org/2001/XMLSchema-instance" xsi:type="termType">
            <count>260192</count>
            <expandedForm>has relationship other than synonymous, narrower, or broader/Associated morphology of</expandedForm>
            <termType>RO/associated_morphology_of</termType>
            <totalCountValidation>0</totalCountValidation>
        </sourceList>
        <sourceList xmlns:xsi="http://www.w3.org/2001/XMLSchema-instance" xsi:type="termType">
            <count>274688</count>
            <expandedForm>has relationship other than synonymous, narrower, or broader/Has method</expandedForm>
            <termType>RO/has_method</termType>
            <totalCountValidation>0</totalCountValidation>
        </sourceList>
        <sourceList xmlns:xsi="http://www.w3.org/2001/XMLSchema-instance" xsi:type="termType">
            <count>274688</count>
            <expandedForm>has relationship other than synonymous, narrower, or broader/Method of</expandedForm>
            <termType>RO/method_of</termType>
            <totalCountValidation>0</totalCountValidation>
        </sourceList>
        <sourceList xmlns:xsi="http://www.w3.org/2001/XMLSchema-instance" xsi:type="termType">
            <count>360310</count>
            <expandedForm>has relationship other than synonymous, narrower, or broader/Finding site of</expandedForm>
            <termType>RO/finding_site_of</termType>
            <totalCountValidation>0</totalCountValidation>
        </sourceList>
        <sourceList xmlns:xsi="http://www.w3.org/2001/XMLSchema-instance" xsi:type="termType">
            <count>360310</count>
            <expandedForm>has relationship other than synonymous, narrower, or broader/Has finding_site</expandedForm>
            <termType>RO/has_finding_site</termType>
            <totalCountValidation>0</totalCountValidation>
        </sourceList>
        <sourceList xmlns:xsi="http://www.w3.org/2001/XMLSchema-instance" xsi:type="termType">
            <count>994499</count>
            <expandedForm>has parent relationship in a Metathesaurus source vocabulary /Inverse is a</expandedForm>
            <termType>PAR/inverse_isa</termType>
            <totalCountValidation>0</totalCountValidation>
        </sourceList>
        <sourceList xmlns:xsi="http://www.w3.org/2001/XMLSchema-instance" xsi:type="termType">
            <count>994499</count>
            <expandedForm>has child relationship in a Metathesaurus source vocabulary /Is a</expandedForm>
            <termType>CHD/isa</termType>
            <totalCountValidation>0</totalCountValidation>
        </sourceList>
    </result>
    <source>SNOMEDCT_US</source>
</statisticalReport>
